{
  "menus": [
    {
      "text": "Dragon Menu",
      "href": "#",
      "icon": "ampersand",
      "menus": [
        {
          "text": "Examples",
          "href": "#",
          "icon": "stackoverflow",
          "menus": [
            {
              "text": "Texts",
              "href": "#texts",
              "icon": "typography"
            },
            {
              "text": "Dates",
              "href": "#dates",
              "icon": "calendar"
            },
            {
              "text": "Administration",
              "href": "#",
              "icon": "equalizer3",
              "menus": [
                {
                  "text": "Users",
                  "href": "#my_user",
                  "icon": "user"
                },
                {
                  "text": "Groups",
                  "href": "#group",
                  "icon": "users4"
                }
              ]
            }
          ]
        }
      ]
    },
    {
      "text": "Extra",
      "href": "#",
      "class": "navigation-header",
      "icon": "menu"
    }
  ]
}
