{
  "ID": "ID",
  "username": "Usuario",
  "password": "Contraseña",
  "login": "Iniciar Sesión",
  "remember": "Recordar",
  "name": "Nombre",
  "ms_product_name": "Producto",
  "ms_user_name": "Usuario",
  "ms_category_name": "Categoría",
  "Company": "Compañía",
  "Security": "Seguridad",
  "SMTP": "SMTP",
  "Database": "Base de datos",
  "config_appName": "Nombre",
  "config_logo": "Texto del logo",
  "config_language": "Lenguaje por defecto",
  "config_appKey": "Llave de la aplicación",
  "config_mode": "Modo de la aplicación",
  "config_home": "Pantalla Principal",
  "config_filePath": "Carpeta de archivos",
  "config_support_email": "Correo",
  "config_support_phone": "Teléfono",
  "config_features_fileManager": "Manejador de archivos",
  "config_features_stepManager": "Manejador de pasos/log",
  "config_features_token": "Seguridad Token",
  "config_features_multilanguage": "Multilenguaje",
  "config_features_onesignal": "OneSignal",
  "config_ui_colors_primary": "Color Principal(Barras)",
  "config_ui_colors_menu": "Color del menu",
  "config_ui_colors_info": "Color del contenido",
  "config_ui_theme_primary": "Color Principal(Barras)",
  "config_ui_theme_secundary": "Color Secundario(Contenido)",
  "config_ui_theme_extra": "Color Extra(Menu)",
  "config_ui_theme_text1": "Texto1 Recomendado(Negro)",
  "config_ui_theme_text2": "Texto2 Recomendado(Blanco)",
  "config_ui_theme_text3": "Texto3 Recomendado(Blanco)",
  "config_ui_theme_primaryShades": "Sombras para el color principal",
  "config_ui_theme_secundaryShades": "Sombras para el color secundario",
  "config_ui_theme_extraShades": "Sombras para el color extra",
  "config_developerBy_name": "Nombre",
  "config_developerBy_profile": "Perfil",
  "config_developerBy_site": "Sitio",
  "config_users_model": "Tabla de usuarios",
  "config_users_engine": "Motor de base de datos",
  "config_users_fields_username": "Campo Usuario",
  "config_users_fields_password": "Campo Contraseña",
  "config_users_expire": "Tiempo de expiración para la sessión",
  "expireExp": "Dias(d),Horas(h),Minutos(M),Segundos(S)",
  "config_users_attempts": "Limite de intentos fallidos",
  "config_users_unlockTime": "Tiempo para desbloqueo(minutos)",
  "config_domain": "Dominio",
  "config_subdomain": "SubDominio",
  "config_port": "Puerto",
  "config_ssl": "SSL",
  "config_googlemap": "Llave para googlemap",
  "config_onesignal_userAuthKey": "Llave de Usuario",
  "config_onesignal_appAuthKey": "Llave de la aplicación",
  "config_onesignal_appId": "ID de la aplicación",
  "config_smtp_host": "Host",
  "config_smtp_port": "Puerto",
  "config_smtp_secure": "SSL",
  "config_smtp_auth_user": "Correo",
  "config_smtp_auth_pass": "Password",
  "config_smptOptions_sender": "Correo que envía",
  "config_smptOptions_name": "Nombre al enviar",
  "config_mssqlactive": "Microsoft SQL Server",
  "config_mysqlactive": "My SQL",
  "config_oracleactive": "Oracle",
  "config_mssql_user": "Usuario",
  "config_mssql_password": "Contraseña",
  "config_mssql_server": "Servidor",
  "config_mssql_database": "Base de datos",
  "config_mssql_port": "Puerto",
  "config_mysql_user": "Usuario",
  "config_mysql_password": "Contraseña",
  "config_mysql_host": "Servidor",
  "config_mysql_database": "Base de datos",
  "config_mysql_port": "Puerto",
  "config_oracle_user": "Usuario",
  "config_oracle_password": "Contraseña",
  "config_oracle_connectString": "TNS",
  "loginSplash": "Fondo del login",
  "newpassword": "Nueva Contraseña",
  "confirmpassword": "Confirmar Contraseña",
  "forgotfield": "Correo",
  "variable": "Variable",
  "type": "Tipo",
  "description": "Descripción",
  "active": "Activo",
  "length": "Longitud",
  "parent": "Padre",
  "elements": "Elementos",
  "multiple": "Es Multiple",
  "isDecimal": "Es Decimal",
  "documentType": "Tipo de Documento",
  "multiplefile": "Multiple Archivos",
  "config_users_hash": "Tipo de Encriptación",
  "config_users_rules_min": "Mínimo de caracteres",
  "config_users_rules_max": "Máximo de caracteres",
  "config_users_rules_number": "Números que debe contener",
  "config_users_rules_mayus": "Mayúsculas que debe contener",
  "config_users_rules_letter": "Letras que debe contener",
  "config_users_rules_specialchar": "Caracteres especiales que debe contener",
  "config_users_rules_notusername": "No debe ser igual al nombre de usuario",
  "config_users_rules_notlast": "No debe ser igual a la ultima contraseña",
  "config_features_customfields": "Campos Personalizados",
  "dragon_customfield": "Campo Personalizado",
  "dragon_customfield_plural": "Campos Personalizados",
  "config_users_rules_expire": "Dias para que expire la contraseña",
  "texts": "Textos",
  "users_plural": "Usuarios",
  "users": "Usuario",
  "id": "id",
  "lastname": "apellido",
  "image": "imágen",
  "email": "correo",
  "created": "creado en",
  "updated": "actualizado en",
  "deleted": "eliminado en",
  "user_created": "creador",
  "user_updated": "actualizador",
  "dragon_configuration_plural": "configuraciones",
  "dragon_configuration": "configuración",
  "logo": "logo",
  "config_features_configuration": "configuración",
  "config_onesignal_app_appAuthKey": "AppAuthKey",
  "config_onesignal_app_appId": "App Id",
  "dragon_group_plural": "grupos",
  "dragon_group": "grupo",
  "profileimage": "imágen de perfil",
  "profile": "perfil",
  "texts_plural": "textos",
  "num": "no.",
  "basic": "básico",
  "money": "dinero",
  "percentage": "porcentaje",
  "readonly": "solo lectura",
  "normalpassword": "password normal",
  "passwordplus": "password mejorada",
  "textarea": "textarea",
  "dates_plural": "fechas",
  "dates": "fechas",
  "date": "fecha",
  "datetime": "fecha y tiempo",
  "time": "tiempo",
  "range_from": "fecha desde",
  "range_to": "fecha hasta",
  "rangetime_from": "rango con fecha y tiempo",
  "rangetime_to": "rango con fecha y tiempo",
  "year": "año",
  "homePage": "página principal",
  "isAdmin": "Es Administrador?",
  "undefined": "Sin Definir",
  "dragon_fieldtype_plural": "Tipos de campo",
  "dragon_fieldtype": "Tipo de campo",
  "dragon_mime_plural": "mimes",
  "dragon_mime": "mime",
  "mask": "mascara",
  "positions": "posiciones",
  "dragon_information_plural": "informaciones",
  "dragon_information": "información",
  "dragon_notifications_plural": "notificaciones",
  "dragon_notifications": "notificación",
  "subject": "tema",
  "content": "contenido",
  "segment_plural": "segmentos",
  "dragon_segment": "segmento",
  "dragon_interval_plural": "intervalos",
  "dragon_interval": "intervalo",
  "segments": "segmentos",
  "showSegments": "Mostrar Segmentos",
  "advance": "avanzado",
  "sendAfter_label": "Enviar despues de",
  "headings": "cabecera",
  "url": "url",
  "schedule": "planificado",
  "count": "cantidad",
  "until_label": "Hasta",
  "language_plural": "lenguajes",
  "dragon_language": "lenguaje",
  "range": "Rango de Fecha",
  "rangetime": "Rango de Fecha y Tiempo",
  "date_label": "Fecha",
  "datetime_label": "Fecha y Tiempo",
  "Dates": "Fechas",
  "dragon_currency_plural": "monedas",
  "dragon_currency": "moneda",
  "symbol": "símbolo",
  "decimal": "decimal",
  "separator": "separador",
  "precision": "presición",
  "curreny_plural": "monedas",
  "format": "formato",
  "phone": "teléfono",
  "config_proxy_domain": "Dominio",
  "config_proxy_subdomain": "Subdominio ",
  "config_proxy_port": "Port",
  "config_proxy_ssl": "Ssl",
  "cellphone": "celular",
  "hour": "horas",
  "integer": "número entero",
  "indentification": "cédula",
  "creditcard": "tarjeta de crédito",
  "blog_plural": "blogs",
  "blog": "blog",
  "_id": "id",
  "article": "articulo",
  "likes": "me gusta",
  "title": "título",
  "topic": "tópico",
  "createdAt": "fecha creación",
  "timerange_from": "tiempo desde",
  "timerange_to": "tiempo hasta",
  "timerange": "rango de tiempo",
  "time_label": "tiempo",
  "lists_plural": "listas",
  "lists": "lista",
  "parent_name": "padre",
  "child_name": "hijo",
  "relation": "relación",
  "parent_plural": "padres",
  "child_plural": "hijos",
  "child": "hijo",
  "relation_plural": "relaciones",
  "special_plural": "especiales",
  "special": "especial",
  "color": "color",
  "location": "localización",
  "bit": "booleano",
  "tags": "etiquetas",
  "html": "html",
  "logica_plural": "logicas",
  "logica": "logica",
  "categories": "categorías",
  "lists_category": "categorías de listas",
  "lists_category_plural": "categorías de listas",
  "category_name": "categoría",
  "lists_name": "lista",
  "category_plural": "categorías",
  "category": "categoría",
  "charts_plural": "Gráficos",
  "charts": "Gráfico",
  "view_report_plural": "Vistas",
  "view_report": "Vista",
  "images": "imágenes",
  "files": "archivos",
  "upload_image": "Subir documentos",
  "dragon_function_plural": "funciones",
  "dragon_function": "función",
  "OneToMany": "Uno a Mucho",
  "ManyToMany": "Mucho a Mucho",
  "dragon_language_plural": "languages",
  "query_plural": "consultas",
  "dragon_function_query_plural": "consultas",
  "dragon_function_query": "consulta",
  "dragon_query": "consulta",
  "parameters": "parámetros",
  "dragon_task_plural": "tareas",
  "dragon_task": "tarea",
  "second": "segundo",
  "minute": "minuto",
  "day": "día",
  "month": "mes",
  "dayOfWeek": "día de la semana",
  "start": "inicio",
  "end": "final",
  "enabled": "activa",
  "script": "código"
}